mobileprint/__init__.py
mobileprint/arguments.py
mobileprint/human_benchmark.py
mobileprint/storage.py
mobileprint/env/Env1D.py
mobileprint/env/Env2D.py
mobileprint/env/__init__.py
mobileprint_test-0.0.1.dist-info/LICENSE
mobileprint_test-0.0.1.dist-info/METADATA
mobileprint_test-0.0.1.dist-info/WHEEL
mobileprint_test-0.0.1.dist-info/top_level.txt
mobileprint_test-0.0.1.dist-info/RECORD
