Metadata-Version: 2.1
Name: mobileprint-test
Version: 0.0.1
Summary: GUI for measuring human performance on mobile construction task
Home-page: http://pypi.python.org/pypi/mobileprint/
Author: NYU AI4CE
Author-email: alexandergao@nyu.edu
License: UNKNOWN
Platform: UNKNOWN
Classifier: Programming Language :: Python :: 3
Classifier: License :: OSI Approved :: MIT License
Classifier: Operating System :: OS Independent
Requires-Python: >=3.6
Requires-Dist: opencv-python (==4.4.0.42)
Requires-Dist: gym (==0.17.2)
Requires-Dist: matplotlib (==3.3.1)
Requires-Dist: numpy (==1.19.1)
